{
  "languages": {
    "pl": "Polski",
    "en": "English"
  },
  "general": {
    "calendar": "Calendar",
    "description": "Description",
    "favourite": "Favourite",
    "feed": "Feed",
    "language": "Language",
    "organizations": "Organizations",
    "organization": "Organization",
    "event": "Event",
    "settings": "Settings",
    "search": "Search",
    "your-organizations": "Your organizations",
    "create-organization": "Create organization",
    "all-events": "All events",
    "less": "Less",
    "more": "More",
    "event-search": "Search Event",
    "organization-search": "Search Organization",
    "login": "Log In",
    "register": "Register",
    "create-event": "Add Event"
  },
  "settings": {
    "account": "Account",
    "language": "Language",
    "notifications": "Notifications",
    "dark-mode": "Dark mode",
    "information": "Information",
    "account-details": {
      "sign-out": "Sign out",
      "name": "User",
      "email": "Email"
    }
  },
  "organization-details": {
    "follow": "Follow",
    "following": "Following"
  },
  "all-events": {
    "upcoming": "Upcoming",
    "past": "Past",
    "see-all": "See all"
  },
  "calendar": {
    "empty-date": "No events on this date.",
    "saved": "Saved",
    "following": "Following",
    "all": "All"
  },
  "searchbar": {
    "placeholder": "Search..."
  },
  "event-details": {
    "last-edit": "Last edited",
    "save": "Save",
    "saved": "Saved"
  },
  "login": {
    "welcome-to": "Welcome to",
    "email-label": "Email",
    "email-placeholder": "email@agh.edu.pl",
    "AGH-domain-email-address": "AGH domain email address",
    "password-label": "Password",
    "password-placeholder": "password",
    "password-min-length-description": "Minimum password length: 8",
    "forgot-password-link": "Forgot password?",
    "sign-in": "Sign in",
    "missing-information": "Missing Information",
    "fill-required-fields": "Please fill in all required fields.",
    "invalid-email": "Invalid Email",
    "valid-email-address": "Please enter a valid email address.",
    "login-failed": "Login Failed",
    "check-email-password": "Please check your email and password.",
    "login-error": "Error during login:",
    "no-account-question": "Do not have an account? ",
    "sign-up": "Sign up!",
    "or": "or",
    "use-agh-account": "Use AGH account",
    "continue-as-guest": "Continue as guest"
  },
  "registration": {
    "email-placeholder": "email@agh.edu.pl",
    "first-name-label": "First name",
    "last-name-label": "Last name",
    "email-label": "Email",
    "password-label": "Password",
    "repeat-password-label": "Repeat password",
    "password-min-length-description": "Minimum password length: 8",
    "password-match-description": "Passwords have to be identical",
    "register-button": "Register",
    "missing-information": "Missing Information",
    "all-fields-required": "Please fill in all required fields",
    "invalid-email": "Invalid Email",
    "registration-failed": "Registration failed",
    "registration-success": "Successfully registered",
    "registration-error": "Registration error:",
    "name-placeholder": "First name",
    "last-name-placeholder": "Last name",
    "agh-domain-email-description": "AGH domain email address",
    "password-placeholder": "Password",
    "invalid-password": "Invalid Password"
  },
  "create-event": {
    "upload-image": "Upload Image",
    "update-image": "Update Image",
    "at-least-one-translation-required-info": "(Values in at least one language need to be provided)",
    "name-label": "Name",
    "provide-event-name": "Provide event name...",
    "description-label": "Description",
    "provide-event-description": "Provide event description...",
    "location-label": "Location",
    "provide-event-location": "Provide event location...",
    "start-date-label": "Start Date",
    "end-date-label": "End Date",
    "set-start-date": "Set Start Date",
    "set-end-date": "Set End Date",
    "submit": "Submit",
    "background-image-required-error": "Event background image is required",
    "at-least-one-translation-required-error": "At least one translation need to be provided",
    "start-date-not-before-end-date-error": "Start date must be before end date",
    "start-date-in-the-past-error": "Start date cannot be in the past",
    "validation-failed-error": "Incorrect data provided. Review the problems and try again.",
    "calendar": {
      "confirm": "Confirm",
      "cancel": "Cancel"
    }
  }
}
